mplugins/__init__.py
mplugins/helper.py
mplugins-0.0.1rc2.dist-info/LICENSE
mplugins-0.0.1rc2.dist-info/METADATA
mplugins-0.0.1rc2.dist-info/WHEEL
mplugins-0.0.1rc2.dist-info/dependency_links.txt
mplugins-0.0.1rc2.dist-info/top_level.txt
mplugins-0.0.1rc2.dist-info/RECORD
